Metadata-Version: 1.1
Name: italian-vip-says
Version: 1.0.0
Summary: Find out what some Italian VIPs really say
Home-page: https://github.com/lotrekagency/italian-vip-says
Author: Lotrek
Author-email: dimmitutto@lotrek.it
License: MIT
Platform: UNKNOWN
Classifier: Programming Language :: Python
Classifier: Programming Language :: Python :: 3
